bibdec/__init__.py
bibdec/bibdec.py
bibdec-0.0.1.dist-info/LICENSE
bibdec-0.0.1.dist-info/METADATA
bibdec-0.0.1.dist-info/WHEEL
bibdec-0.0.1.dist-info/top_level.txt
bibdec-0.0.1.dist-info/RECORD
