Metadata-Version: 2.1
Name: bibdec
Version: 0.0.1
Summary: A decorator used to automatically generate citations from Python code
Home-page: https://github.com/yngvem/bibdec
Author: Yngve Mardal Moe
Author-email: yngve.m.moe@gmail.com
License: "MIT license",
Keywords: bibdec
Platform: UNKNOWN
Classifier: Development Status :: 2 - Pre-Alpha
Classifier: Intended Audience :: Developers
Classifier: License :: OSI Approved :: MIT License
Classifier: Natural Language :: English
Classifier: Programming Language :: Python :: 3.6
Classifier: Programming Language :: Python :: 3.7
Requires-Dist: bibtexparser
